PythonCookbookZhongwenban/README.md
PythonCookbookZhongwenban/__init__.py
PythonCookbookZhongwenban/__main__.py
PythonCookbookZhongwenban/file.epub
PythonCookbookZhongwenban/index.html
PythonCookbookZhongwenban/css/__init__.py
PythonCookbookZhongwenban/css/annotations.css
PythonCookbookZhongwenban/css/main.css
PythonCookbookZhongwenban/css/normalize.css
PythonCookbookZhongwenban/css/popup.css
PythonCookbookZhongwenban/font/__init__.py
PythonCookbookZhongwenban/font/fontello.eot
PythonCookbookZhongwenban/font/fontello.svg
PythonCookbookZhongwenban/font/fontello.ttf
PythonCookbookZhongwenban/font/fontello.woff
PythonCookbookZhongwenban/img/__init__.py
PythonCookbookZhongwenban/img/annotator-glyph-sprite.png
PythonCookbookZhongwenban/img/annotator-icon-sprite.png
PythonCookbookZhongwenban/img/apple-touch-icon.png
PythonCookbookZhongwenban/img/cancelfullscreen.png
PythonCookbookZhongwenban/img/close.png
PythonCookbookZhongwenban/img/fullscreen.png
PythonCookbookZhongwenban/img/loader.gif
PythonCookbookZhongwenban/img/menu-icon.png
PythonCookbookZhongwenban/img/save.png
PythonCookbookZhongwenban/img/saved.png
PythonCookbookZhongwenban/img/settings-s.png
PythonCookbookZhongwenban/img/settings.png
PythonCookbookZhongwenban/img/star.png
PythonCookbookZhongwenban/js/__init__.py
PythonCookbookZhongwenban/js/epub.js
PythonCookbookZhongwenban/js/epub.min.js
PythonCookbookZhongwenban/js/epub.min.map
PythonCookbookZhongwenban/js/hooks.min.js
PythonCookbookZhongwenban/js/hooks.min.map
PythonCookbookZhongwenban/js/reader.js
PythonCookbookZhongwenban/js/reader.js.map
PythonCookbookZhongwenban/js/reader.min.js
PythonCookbookZhongwenban/js/reader.min.map
PythonCookbookZhongwenban/js/hooks/__init__.py
PythonCookbookZhongwenban/js/hooks/extensions/__init__.py
PythonCookbookZhongwenban/js/hooks/extensions/highlight.js
PythonCookbookZhongwenban/js/libs/__init__.py
PythonCookbookZhongwenban/js/libs/jquery.min.js
PythonCookbookZhongwenban/js/libs/localforage.min.js
python_cookbook_zhongwenban-2024.3.2.0.dist-info/METADATA
python_cookbook_zhongwenban-2024.3.2.0.dist-info/WHEEL
python_cookbook_zhongwenban-2024.3.2.0.dist-info/entry_points.txt
python_cookbook_zhongwenban-2024.3.2.0.dist-info/top_level.txt
python_cookbook_zhongwenban-2024.3.2.0.dist-info/RECORD
